pyllas/__init__.py
pyllas/client.py
pyllas/sql.py
pyllas/storage/__init__.py
pyllas/storage/paths.py
pyllas/storage/s3.py
pyllas/utils/__init__.py
pyllas/utils/logger.py
pyllas/utils/progress_bar.py
pyllas-0.4.0.dist-info/LICENSE
pyllas-0.4.0.dist-info/METADATA
pyllas-0.4.0.dist-info/WHEEL
pyllas-0.4.0.dist-info/top_level.txt
pyllas-0.4.0.dist-info/RECORD
