Metadata-Version: 2.1
Name: pyllas
Version: 0.4.0
Summary: Client for AWS Athena
Home-page: https://github.com/wristylotus/Pyllas
Author: wristylotus
Author-email: wristylotus@gmail.com
Project-URL: Documentation, https://github.com/wristylotus/Pyllas/blob/main/README.md
Keywords: pyllas aws athena sql jupyter
Classifier: Programming Language :: Python :: 3.8
Classifier: License :: OSI Approved :: MIT License
Classifier: Operating System :: OS Independent
Requires-Python: >=3.8
License-File: LICENSE
Requires-Dist: boto3 ~=1.24.9
Requires-Dist: botocore ~=1.27.96
Requires-Dist: pandas ~=1.5.0
Requires-Dist: pyarrow ~=8.0.0
